giso/__init__.py
giso/_cli.py
giso/_core.py
giso/data/ne_10m_admin_1_states_provinces.parquet
giso-1.0.0.dist-info/METADATA
giso-1.0.0.dist-info/WHEEL
giso-1.0.0.dist-info/entry_points.txt
giso-1.0.0.dist-info/licenses/LICENSE
giso-1.0.0.dist-info/RECORD
