Metadata-Version: 2.4
Name: giso
Version: 1.0.0
Summary: A simple command line tool to help with geocoding country/region ISO 3166-2 codes
Project-URL: homepage, https://pypi.org/project/giso/
Project-URL: repository, https://github.com/corbel-spatial/giso
Project-URL: issues, https://github.com/corbel-spatial/giso/issues
Project-URL: changelog, https://github.com/corbel-spatial/giso/blob/main/CHANGELOG.md
Author-email: Peter Von der Porten <dev@corbelspatial.com>
License-Expression: MIT
License-File: LICENSE
Classifier: Development Status :: 4 - Beta
Classifier: Intended Audience :: Information Technology
Classifier: Operating System :: MacOS
Classifier: Operating System :: Microsoft :: Windows :: Windows 10
Classifier: Operating System :: Microsoft :: Windows :: Windows 11
Classifier: Operating System :: OS Independent
Classifier: Operating System :: POSIX :: Linux
Classifier: Programming Language :: Python :: 3.10
Classifier: Programming Language :: Python :: 3.11
Classifier: Programming Language :: Python :: 3.12
Classifier: Programming Language :: Python :: 3.13
Classifier: Programming Language :: Python :: 3.14
Classifier: Topic :: Scientific/Engineering :: GIS
Requires-Python: >=3.10
Requires-Dist: apache-sedona[db]<2,>=1.8.0
Requires-Dist: click
Requires-Dist: geopandas>=1.1.0
Requires-Dist: pyarrow
